.gitattributes
.gitignore
CHANGELOG.rst
LICENSE.txt
MANIFEST.in
README.rst
requirements.txt
run_tests.py
setup.py
setup_cx_freeze.py
setup_py2app.py
assets/DS_Store
assets/background.pdf
assets/create_dmg.sh
assets/create_installer.iss
assets/create_installer.iss.base
assets/crispy.icns
assets/crispy.ico
crispy/__init__.py
crispy/__main__.py
crispy/version.py
crispy.egg-info/PKG-INFO
crispy.egg-info/SOURCES.txt
crispy.egg-info/dependency_links.txt
crispy.egg-info/requires.txt
crispy.egg-info/top_level.txt
crispy/gui/__init__.py
crispy/gui/config.py
crispy/gui/main.py
crispy/gui/models.py
crispy/gui/plot.py
crispy/gui/quanty.py
crispy/gui/views.py
crispy/gui/widgets.py
crispy/gui/icons/__init__.py
crispy/gui/icons/clipboard.svg
crispy/gui/icons/cog.svg
crispy/gui/icons/crispy.svg
crispy/gui/icons/folder-open.svg
crispy/gui/icons/play.svg
crispy/gui/icons/save.svg
crispy/gui/icons/stop.svg
crispy/gui/icons/trash.svg
crispy/gui/uis/__init__.py
crispy/gui/uis/about.ui
crispy/gui/uis/main.ui
crispy/gui/uis/update.ui
crispy/gui/uis/quanty/__init__.py
crispy/gui/uis/quanty/details.ui
crispy/gui/uis/quanty/main.ui
crispy/gui/uis/quanty/preferences.ui
crispy/modules/__init__.py
crispy/modules/orca/__init__.py
crispy/modules/orca/parser.py
crispy/modules/quanty/__init__.py
crispy/modules/quanty/parameters/parameters.json.gz
crispy/modules/quanty/templates/3d_C3v_RIXS_1s2p.lua
crispy/modules/quanty/templates/3d_C3v_RIXS_1s3p.lua
crispy/modules/quanty/templates/3d_C3v_RIXS_2p3d.lua
crispy/modules/quanty/templates/3d_C3v_XAS_1s.lua
crispy/modules/quanty/templates/3d_C3v_XAS_2p.lua
crispy/modules/quanty/templates/3d_C3v_XAS_2s.lua
crispy/modules/quanty/templates/3d_C3v_XAS_3p.lua
crispy/modules/quanty/templates/3d_C3v_XAS_3s.lua
crispy/modules/quanty/templates/3d_C3v_XES_1s2p.lua
crispy/modules/quanty/templates/3d_C3v_XES_1s3p.lua
crispy/modules/quanty/templates/3d_C3v_XPS_1s.lua
crispy/modules/quanty/templates/3d_C3v_XPS_2p.lua
crispy/modules/quanty/templates/3d_C3v_XPS_2s.lua
crispy/modules/quanty/templates/3d_C3v_XPS_3p.lua
crispy/modules/quanty/templates/3d_C3v_XPS_3s.lua
