Metadata-Version: 2.1
Name: crispy
Version: 0.7.4
Summary: Core-Level Spectroscopy Simulations in Python
Home-page: https://github.com/mretegan/crispy
Author: Marius Retegan
Author-email: marius.retegan@esrf.eu
License: MIT
Download-URL: https://github.com/mretegan/crispy/releases
Keywords: gui,spectroscopy,simulation,synchrotron,science
Platform: MacOS :: MacOS X
Platform: Microsoft :: Windows
Platform: POSIX :: Linux
Classifier: Development Status :: 4 - Beta
Classifier: Environment :: X11 Applications :: Qt
Classifier: Intended Audience :: Education
Classifier: Intended Audience :: Science/Research
Classifier: License :: OSI Approved :: MIT License
Classifier: Operating System :: MacOS :: MacOS X
Classifier: Operating System :: Microsoft :: Windows
Classifier: Operating System :: POSIX :: Linux
Classifier: Programming Language :: Python :: 2.7
Classifier: Programming Language :: Python :: 3.4
Classifier: Programming Language :: Python :: 3.5
Classifier: Programming Language :: Python :: 3.6
Classifier: Programming Language :: Python :: 3.7
Classifier: Topic :: Scientific/Engineering :: Visualization
License-File: LICENSE.txt
